setup.py
binomial_package_distributions/Binomialdistribution.py
binomial_package_distributions/Gaussiandistribution.py
binomial_package_distributions/Generaldistribution.py
binomial_package_distributions/__init__.py
binomial_package_distributions.egg-info/PKG-INFO
binomial_package_distributions.egg-info/SOURCES.txt
binomial_package_distributions.egg-info/dependency_links.txt
binomial_package_distributions.egg-info/not-zip-safe
binomial_package_distributions.egg-info/top_level.txt