Metadata-Version: 1.0
Name: binomial-package-distributions
Version: 0.1
Summary: Gaussian distributions
Home-page: UNKNOWN
Author: Abhishek
Author-email: UNKNOWN
License: UNKNOWN
Platform: UNKNOWN
